{
  "results": [
    {
      "seed": 4000,
      "template": "timestomp",
      "mode": "normal",
      "ok": true,
      "wall_s": 11.31,
      "chain_ok": true,
      "chain_reason": null,
      "tp": 1,
      "fp": 0,
      "fn": 0,
      "fp_planted": 0,
      "precision": 1.0,
      "recall": 1.0,
      "f1": 1.0,
      "n_findings": 1
    },
    {
      "seed": 4001,
      "template": "timestomp",
      "mode": "normal",
      "ok": true,
      "wall_s": 10.15,
      "chain_ok": true,
      "chain_reason": null,
      "tp": 1,
      "fp": 0,
      "fn": 0,
      "fp_planted": 0,
      "precision": 1.0,
      "recall": 1.0,
      "f1": 1.0,
      "n_findings": 1
    },
    {
      "seed": 4002,
      "template": "timestomp",
      "mode": "normal",
      "ok": true,
      "wall_s": 11.04,
      "chain_ok": true,
      "chain_reason": null,
      "tp": 1,
      "fp": 0,
      "fn": 0,
      "fp_planted": 0,
      "precision": 1.0,
      "recall": 1.0,
      "f1": 1.0,
      "n_findings": 1
    },
    {
      "seed": 4003,
      "template": "timestomp",
      "mode": "normal",
      "ok": true,
      "wall_s": 10.75,
      "chain_ok": true,
      "chain_reason": null,
      "tp": 1,
      "fp": 0,
      "fn": 0,
      "fp_planted": 0,
      "precision": 1.0,
      "recall": 1.0,
      "f1": 1.0,
      "n_findings": 1
    },
    {
      "seed": 4004,
      "template": "timestomp",
      "mode": "normal",
      "ok": true,
      "wall_s": 10.39,
      "chain_ok": true,
      "chain_reason": null,
      "tp": 1,
      "fp": 0,
      "fn": 0,
      "fp_planted": 0,
      "precision": 1.0,
      "recall": 1.0,
      "f1": 1.0,
      "n_findings": 1
    },
    {
      "seed": 4005,
      "template": "timestomp",
      "mode": "normal",
      "ok": true,
      "wall_s": 9.9,
      "chain_ok": true,
      "chain_reason": null,
      "tp": 1,
      "fp": 0,
      "fn": 0,
      "fp_planted": 0,
      "precision": 1.0,
      "recall": 1.0,
      "f1": 1.0,
      "n_findings": 1
    },
    {
      "seed": 4006,
      "template": "timestomp",
      "mode": "normal",
      "ok": true,
      "wall_s": 12.1,
      "chain_ok": true,
      "chain_reason": null,
      "tp": 1,
      "fp": 0,
      "fn": 0,
      "fp_planted": 0,
      "precision": 1.0,
      "recall": 1.0,
      "f1": 1.0,
      "n_findings": 1
    },
    {
      "seed": 4007,
      "template": "timestomp",
      "mode": "normal",
      "ok": true,
      "wall_s": 12.75,
      "chain_ok": true,
      "chain_reason": null,
      "tp": 1,
      "fp": 0,
      "fn": 0,
      "fp_planted": 0,
      "precision": 1.0,
      "recall": 1.0,
      "f1": 1.0,
      "n_findings": 1
    },
    {
      "seed": 4008,
      "template": "timestomp",
      "mode": "normal",
      "ok": true,
      "wall_s": 8.92,
      "chain_ok": true,
      "chain_reason": null,
      "tp": 1,
      "fp": 0,
      "fn": 0,
      "fp_planted": 0,
      "precision": 1.0,
      "recall": 1.0,
      "f1": 1.0,
      "n_findings": 1
    },
    {
      "seed": 4009,
      "template": "timestomp",
      "mode": "normal",
      "ok": true,
      "wall_s": 11.36,
      "chain_ok": true,
      "chain_reason": null,
      "tp": 1,
      "fp": 0,
      "fn": 0,
      "fp_planted": 0,
      "precision": 1.0,
      "recall": 1.0,
      "f1": 1.0,
      "n_findings": 1
    },
    {
      "seed": 4010,
      "template": "timestomp",
      "mode": "normal",
      "ok": true,
      "wall_s": 11.97,
      "chain_ok": true,
      "chain_reason": null,
      "tp": 1,
      "fp": 0,
      "fn": 0,
      "fp_planted": 0,
      "precision": 1.0,
      "recall": 1.0,
      "f1": 1.0,
      "n_findings": 1
    },
    {
      "seed": 4011,
      "template": "timestomp",
      "mode": "normal",
      "ok": true,
      "wall_s": 12.97,
      "chain_ok": true,
      "chain_reason": null,
      "tp": 1,
      "fp": 0,
      "fn": 0,
      "fp_planted": 0,
      "precision": 1.0,
      "recall": 1.0,
      "f1": 1.0,
      "n_findings": 1
    },
    {
      "seed": 4012,
      "template": "timestomp",
      "mode": "normal",
      "ok": true,
      "wall_s": 8.33,
      "chain_ok": true,
      "chain_reason": null,
      "tp": 1,
      "fp": 0,
      "fn": 0,
      "fp_planted": 0,
      "precision": 1.0,
      "recall": 1.0,
      "f1": 1.0,
      "n_findings": 1
    },
    {
      "seed": 4013,
      "template": "timestomp",
      "mode": "normal",
      "ok": true,
      "wall_s": 13.39,
      "chain_ok": true,
      "chain_reason": null,
      "tp": 1,
      "fp": 0,
      "fn": 0,
      "fp_planted": 0,
      "precision": 1.0,
      "recall": 1.0,
      "f1": 1.0,
      "n_findings": 1
    },
    {
      "seed": 4014,
      "template": "timestomp",
      "mode": "normal",
      "ok": true,
      "wall_s": 12.61,
      "chain_ok": true,
      "chain_reason": null,
      "tp": 0,
      "fp": 0,
      "fn": 1,
      "fp_planted": 0,
      "precision": 0.0,
      "recall": 0.0,
      "f1": 0.0,
      "n_findings": 0
    },
    {
      "seed": 4015,
      "template": "timestomp",
      "mode": "normal",
      "ok": true,
      "wall_s": 11.05,
      "chain_ok": true,
      "chain_reason": null,
      "tp": 1,
      "fp": 0,
      "fn": 0,
      "fp_planted": 0,
      "precision": 1.0,
      "recall": 1.0,
      "f1": 1.0,
      "n_findings": 1
    },
    {
      "seed": 4016,
      "template": "timestomp",
      "mode": "normal",
      "ok": true,
      "wall_s": 13.23,
      "chain_ok": true,
      "chain_reason": null,
      "tp": 1,
      "fp": 0,
      "fn": 0,
      "fp_planted": 0,
      "precision": 1.0,
      "recall": 1.0,
      "f1": 1.0,
      "n_findings": 1
    },
    {
      "seed": 4017,
      "template": "timestomp",
      "mode": "normal",
      "ok": true,
      "wall_s": 13.21,
      "chain_ok": true,
      "chain_reason": null,
      "tp": 1,
      "fp": 0,
      "fn": 0,
      "fp_planted": 0,
      "precision": 1.0,
      "recall": 1.0,
      "f1": 1.0,
      "n_findings": 1
    },
    {
      "seed": 4018,
      "template": "timestomp",
      "mode": "normal",
      "ok": true,
      "wall_s": 14.24,
      "chain_ok": true,
      "chain_reason": null,
      "tp": 1,
      "fp": 0,
      "fn": 0,
      "fp_planted": 0,
      "precision": 1.0,
      "recall": 1.0,
      "f1": 1.0,
      "n_findings": 1
    },
    {
      "seed": 4019,
      "template": "timestomp",
      "mode": "normal",
      "ok": true,
      "wall_s": 10.32,
      "chain_ok": true,
      "chain_reason": null,
      "tp": 1,
      "fp": 0,
      "fn": 0,
      "fp_planted": 0,
      "precision": 1.0,
      "recall": 1.0,
      "f1": 1.0,
      "n_findings": 1
    },
    {
      "seed": 4000,
      "template": "timestomp",
      "mode": "provocateur",
      "ok": true,
      "wall_s": 10.75,
      "chain_ok": true,
      "chain_reason": null,
      "tp": 0,
      "fp": 0,
      "fn": 1,
      "fp_planted": 0,
      "precision": 0.0,
      "recall": 0.0,
      "f1": 0.0,
      "n_findings": 0
    },
    {
      "seed": 4001,
      "template": "timestomp",
      "mode": "provocateur",
      "ok": true,
      "wall_s": 11.32,
      "chain_ok": true,
      "chain_reason": null,
      "tp": 0,
      "fp": 0,
      "fn": 1,
      "fp_planted": 0,
      "precision": 0.0,
      "recall": 0.0,
      "f1": 0.0,
      "n_findings": 0
    },
    {
      "seed": 4002,
      "template": "timestomp",
      "mode": "provocateur",
      "ok": true,
      "wall_s": 10.49,
      "chain_ok": true,
      "chain_reason": null,
      "tp": 0,
      "fp": 0,
      "fn": 1,
      "fp_planted": 0,
      "precision": 0.0,
      "recall": 0.0,
      "f1": 0.0,
      "n_findings": 0
    },
    {
      "seed": 4003,
      "template": "timestomp",
      "mode": "provocateur",
      "ok": true,
      "wall_s": 13.63,
      "chain_ok": true,
      "chain_reason": null,
      "tp": 1,
      "fp": 0,
      "fn": 0,
      "fp_planted": 0,
      "precision": 1.0,
      "recall": 1.0,
      "f1": 1.0,
      "n_findings": 1
    },
    {
      "seed": 4004,
      "template": "timestomp",
      "mode": "provocateur",
      "ok": true,
      "wall_s": 13.4,
      "chain_ok": true,
      "chain_reason": null,
      "tp": 1,
      "fp": 0,
      "fn": 0,
      "fp_planted": 0,
      "precision": 1.0,
      "recall": 1.0,
      "f1": 1.0,
      "n_findings": 1
    },
    {
      "seed": 4005,
      "template": "timestomp",
      "mode": "provocateur",
      "ok": true,
      "wall_s": 9.22,
      "chain_ok": true,
      "chain_reason": null,
      "tp": 0,
      "fp": 0,
      "fn": 1,
      "fp_planted": 0,
      "precision": 0.0,
      "recall": 0.0,
      "f1": 0.0,
      "n_findings": 0
    },
    {
      "seed": 4006,
      "template": "timestomp",
      "mode": "provocateur",
      "ok": true,
      "wall_s": 13.53,
      "chain_ok": true,
      "chain_reason": null,
      "tp": 1,
      "fp": 0,
      "fn": 0,
      "fp_planted": 0,
      "precision": 1.0,
      "recall": 1.0,
      "f1": 1.0,
      "n_findings": 1
    },
    {
      "seed": 4007,
      "template": "timestomp",
      "mode": "provocateur",
      "ok": true,
      "wall_s": 18.11,
      "chain_ok": true,
      "chain_reason": null,
      "tp": 1,
      "fp": 0,
      "fn": 0,
      "fp_planted": 0,
      "precision": 1.0,
      "recall": 1.0,
      "f1": 1.0,
      "n_findings": 1
    },
    {
      "seed": 4008,
      "template": "timestomp",
      "mode": "provocateur",
      "ok": true,
      "wall_s": 15.97,
      "chain_ok": true,
      "chain_reason": null,
      "tp": 1,
      "fp": 0,
      "fn": 0,
      "fp_planted": 0,
      "precision": 1.0,
      "recall": 1.0,
      "f1": 1.0,
      "n_findings": 1
    },
    {
      "seed": 4009,
      "template": "timestomp",
      "mode": "provocateur",
      "ok": true,
      "wall_s": 13.47,
      "chain_ok": true,
      "chain_reason": null,
      "tp": 1,
      "fp": 0,
      "fn": 0,
      "fp_planted": 0,
      "precision": 1.0,
      "recall": 1.0,
      "f1": 1.0,
      "n_findings": 1
    },
    {
      "seed": 4010,
      "template": "timestomp",
      "mode": "provocateur",
      "ok": true,
      "wall_s": 10.09,
      "chain_ok": true,
      "chain_reason": null,
      "tp": 0,
      "fp": 0,
      "fn": 1,
      "fp_planted": 0,
      "precision": 0.0,
      "recall": 0.0,
      "f1": 0.0,
      "n_findings": 0
    },
    {
      "seed": 4011,
      "template": "timestomp",
      "mode": "provocateur",
      "ok": true,
      "wall_s": 14.13,
      "chain_ok": true,
      "chain_reason": null,
      "tp": 1,
      "fp": 0,
      "fn": 0,
      "fp_planted": 0,
      "precision": 1.0,
      "recall": 1.0,
      "f1": 1.0,
      "n_findings": 1
    },
    {
      "seed": 4012,
      "template": "timestomp",
      "mode": "provocateur",
      "ok": true,
      "wall_s": 10.94,
      "chain_ok": true,
      "chain_reason": null,
      "tp": 1,
      "fp": 0,
      "fn": 0,
      "fp_planted": 0,
      "precision": 1.0,
      "recall": 1.0,
      "f1": 1.0,
      "n_findings": 1
    },
    {
      "seed": 4013,
      "template": "timestomp",
      "mode": "provocateur",
      "ok": true,
      "wall_s": 14.54,
      "chain_ok": true,
      "chain_reason": null,
      "tp": 1,
      "fp": 0,
      "fn": 0,
      "fp_planted": 0,
      "precision": 1.0,
      "recall": 1.0,
      "f1": 1.0,
      "n_findings": 1
    },
    {
      "seed": 4014,
      "template": "timestomp",
      "mode": "provocateur",
      "ok": true,
      "wall_s": 9.32,
      "chain_ok": true,
      "chain_reason": null,
      "tp": 1,
      "fp": 0,
      "fn": 0,
      "fp_planted": 0,
      "precision": 1.0,
      "recall": 1.0,
      "f1": 1.0,
      "n_findings": 1
    },
    {
      "seed": 4015,
      "template": "timestomp",
      "mode": "provocateur",
      "ok": true,
      "wall_s": 11.37,
      "chain_ok": true,
      "chain_reason": null,
      "tp": 1,
      "fp": 0,
      "fn": 0,
      "fp_planted": 0,
      "precision": 1.0,
      "recall": 1.0,
      "f1": 1.0,
      "n_findings": 1
    },
    {
      "seed": 4016,
      "template": "timestomp",
      "mode": "provocateur",
      "ok": true,
      "wall_s": 11.69,
      "chain_ok": true,
      "chain_reason": null,
      "tp": 1,
      "fp": 0,
      "fn": 0,
      "fp_planted": 0,
      "precision": 1.0,
      "recall": 1.0,
      "f1": 1.0,
      "n_findings": 1
    },
    {
      "seed": 4017,
      "template": "timestomp",
      "mode": "provocateur",
      "ok": true,
      "wall_s": 8.39,
      "chain_ok": true,
      "chain_reason": null,
      "tp": 0,
      "fp": 0,
      "fn": 1,
      "fp_planted": 0,
      "precision": 0.0,
      "recall": 0.0,
      "f1": 0.0,
      "n_findings": 0
    },
    {
      "seed": 4018,
      "template": "timestomp",
      "mode": "provocateur",
      "ok": true,
      "wall_s": 13.09,
      "chain_ok": true,
      "chain_reason": null,
      "tp": 1,
      "fp": 0,
      "fn": 0,
      "fp_planted": 0,
      "precision": 1.0,
      "recall": 1.0,
      "f1": 1.0,
      "n_findings": 1
    },
    {
      "seed": 4019,
      "template": "timestomp",
      "mode": "provocateur",
      "ok": true,
      "wall_s": 10.75,
      "chain_ok": true,
      "chain_reason": null,
      "tp": 1,
      "fp": 0,
      "fn": 0,
      "fp_planted": 0,
      "precision": 1.0,
      "recall": 1.0,
      "f1": 1.0,
      "n_findings": 1
    },
    {
      "seed": 4000,
      "template": "registry_persistence",
      "mode": "normal",
      "ok": true,
      "wall_s": 11.08,
      "chain_ok": true,
      "chain_reason": null,
      "tp": 1,
      "fp": 0,
      "fn": 0,
      "fp_planted": 0,
      "precision": 1.0,
      "recall": 1.0,
      "f1": 1.0,
      "n_findings": 1
    },
    {
      "seed": 4001,
      "template": "registry_persistence",
      "mode": "normal",
      "ok": true,
      "wall_s": 11.67,
      "chain_ok": true,
      "chain_reason": null,
      "tp": 1,
      "fp": 0,
      "fn": 0,
      "fp_planted": 0,
      "precision": 1.0,
      "recall": 1.0,
      "f1": 1.0,
      "n_findings": 1
    },
    {
      "seed": 4002,
      "template": "registry_persistence",
      "mode": "normal",
      "ok": true,
      "wall_s": 9.92,
      "chain_ok": true,
      "chain_reason": null,
      "tp": 1,
      "fp": 0,
      "fn": 0,
      "fp_planted": 0,
      "precision": 1.0,
      "recall": 1.0,
      "f1": 1.0,
      "n_findings": 1
    },
    {
      "seed": 4003,
      "template": "registry_persistence",
      "mode": "normal",
      "ok": true,
      "wall_s": 11.78,
      "chain_ok": true,
      "chain_reason": null,
      "tp": 1,
      "fp": 0,
      "fn": 0,
      "fp_planted": 0,
      "precision": 1.0,
      "recall": 1.0,
      "f1": 1.0,
      "n_findings": 1
    },
    {
      "seed": 4004,
      "template": "registry_persistence",
      "mode": "normal",
      "ok": true,
      "wall_s": 11.69,
      "chain_ok": true,
      "chain_reason": null,
      "tp": 0,
      "fp": 0,
      "fn": 1,
      "fp_planted": 0,
      "precision": 0.0,
      "recall": 0.0,
      "f1": 0.0,
      "n_findings": 0
    },
    {
      "seed": 4005,
      "template": "registry_persistence",
      "mode": "normal",
      "ok": true,
      "wall_s": 9.73,
      "chain_ok": true,
      "chain_reason": null,
      "tp": 1,
      "fp": 0,
      "fn": 0,
      "fp_planted": 0,
      "precision": 1.0,
      "recall": 1.0,
      "f1": 1.0,
      "n_findings": 1
    },
    {
      "seed": 4006,
      "template": "registry_persistence",
      "mode": "normal",
      "ok": true,
      "wall_s": 9.72,
      "chain_ok": true,
      "chain_reason": null,
      "tp": 1,
      "fp": 0,
      "fn": 0,
      "fp_planted": 0,
      "precision": 1.0,
      "recall": 1.0,
      "f1": 1.0,
      "n_findings": 1
    },
    {
      "seed": 4007,
      "template": "registry_persistence",
      "mode": "normal",
      "ok": true,
      "wall_s": 9.1,
      "chain_ok": true,
      "chain_reason": null,
      "tp": 1,
      "fp": 0,
      "fn": 0,
      "fp_planted": 0,
      "precision": 1.0,
      "recall": 1.0,
      "f1": 1.0,
      "n_findings": 1
    },
    {
      "seed": 4008,
      "template": "registry_persistence",
      "mode": "normal",
      "ok": true,
      "wall_s": 10.97,
      "chain_ok": true,
      "chain_reason": null,
      "tp": 1,
      "fp": 0,
      "fn": 0,
      "fp_planted": 0,
      "precision": 1.0,
      "recall": 1.0,
      "f1": 1.0,
      "n_findings": 1
    },
    {
      "seed": 4009,
      "template": "registry_persistence",
      "mode": "normal",
      "ok": true,
      "wall_s": 12.99,
      "chain_ok": true,
      "chain_reason": null,
      "tp": 1,
      "fp": 0,
      "fn": 0,
      "fp_planted": 0,
      "precision": 1.0,
      "recall": 1.0,
      "f1": 1.0,
      "n_findings": 1
    },
    {
      "seed": 4010,
      "template": "registry_persistence",
      "mode": "normal",
      "ok": true,
      "wall_s": 9.82,
      "chain_ok": true,
      "chain_reason": null,
      "tp": 1,
      "fp": 0,
      "fn": 0,
      "fp_planted": 0,
      "precision": 1.0,
      "recall": 1.0,
      "f1": 1.0,
      "n_findings": 1
    },
    {
      "seed": 4011,
      "template": "registry_persistence",
      "mode": "normal",
      "ok": true,
      "wall_s": 8.69,
      "chain_ok": true,
      "chain_reason": null,
      "tp": 1,
      "fp": 0,
      "fn": 0,
      "fp_planted": 0,
      "precision": 1.0,
      "recall": 1.0,
      "f1": 1.0,
      "n_findings": 1
    },
    {
      "seed": 4012,
      "template": "registry_persistence",
      "mode": "normal",
      "ok": true,
      "wall_s": 8.81,
      "chain_ok": true,
      "chain_reason": null,
      "tp": 1,
      "fp": 0,
      "fn": 0,
      "fp_planted": 0,
      "precision": 1.0,
      "recall": 1.0,
      "f1": 1.0,
      "n_findings": 1
    },
    {
      "seed": 4013,
      "template": "registry_persistence",
      "mode": "normal",
      "ok": true,
      "wall_s": 11.56,
      "chain_ok": true,
      "chain_reason": null,
      "tp": 1,
      "fp": 0,
      "fn": 0,
      "fp_planted": 0,
      "precision": 1.0,
      "recall": 1.0,
      "f1": 1.0,
      "n_findings": 1
    },
    {
      "seed": 4014,
      "template": "registry_persistence",
      "mode": "normal",
      "ok": true,
      "wall_s": 9.6,
      "chain_ok": true,
      "chain_reason": null,
      "tp": 1,
      "fp": 0,
      "fn": 0,
      "fp_planted": 0,
      "precision": 1.0,
      "recall": 1.0,
      "f1": 1.0,
      "n_findings": 1
    },
    {
      "seed": 4015,
      "template": "registry_persistence",
      "mode": "normal",
      "ok": true,
      "wall_s": 11.36,
      "chain_ok": true,
      "chain_reason": null,
      "tp": 1,
      "fp": 0,
      "fn": 0,
      "fp_planted": 0,
      "precision": 1.0,
      "recall": 1.0,
      "f1": 1.0,
      "n_findings": 1
    },
    {
      "seed": 4016,
      "template": "registry_persistence",
      "mode": "normal",
      "ok": true,
      "wall_s": 8.04,
      "chain_ok": true,
      "chain_reason": null,
      "tp": 1,
      "fp": 0,
      "fn": 0,
      "fp_planted": 0,
      "precision": 1.0,
      "recall": 1.0,
      "f1": 1.0,
      "n_findings": 1
    },
    {
      "seed": 4017,
      "template": "registry_persistence",
      "mode": "normal",
      "ok": true,
      "wall_s": 11.09,
      "chain_ok": true,
      "chain_reason": null,
      "tp": 1,
      "fp": 0,
      "fn": 0,
      "fp_planted": 0,
      "precision": 1.0,
      "recall": 1.0,
      "f1": 1.0,
      "n_findings": 1
    },
    {
      "seed": 4018,
      "template": "registry_persistence",
      "mode": "normal",
      "ok": true,
      "wall_s": 10.14,
      "chain_ok": true,
      "chain_reason": null,
      "tp": 1,
      "fp": 0,
      "fn": 0,
      "fp_planted": 0,
      "precision": 1.0,
      "recall": 1.0,
      "f1": 1.0,
      "n_findings": 1
    },
    {
      "seed": 4019,
      "template": "registry_persistence",
      "mode": "normal",
      "ok": true,
      "wall_s": 9.11,
      "chain_ok": true,
      "chain_reason": null,
      "tp": 1,
      "fp": 0,
      "fn": 0,
      "fp_planted": 0,
      "precision": 1.0,
      "recall": 1.0,
      "f1": 1.0,
      "n_findings": 1
    },
    {
      "seed": 4000,
      "template": "registry_persistence",
      "mode": "provocateur",
      "ok": true,
      "wall_s": 9.62,
      "chain_ok": true,
      "chain_reason": null,
      "tp": 0,
      "fp": 0,
      "fn": 1,
      "fp_planted": 0,
      "precision": 0.0,
      "recall": 0.0,
      "f1": 0.0,
      "n_findings": 0
    },
    {
      "seed": 4001,
      "template": "registry_persistence",
      "mode": "provocateur",
      "ok": true,
      "wall_s": 8.17,
      "chain_ok": true,
      "chain_reason": null,
      "tp": 0,
      "fp": 0,
      "fn": 1,
      "fp_planted": 0,
      "precision": 0.0,
      "recall": 0.0,
      "f1": 0.0,
      "n_findings": 0
    },
    {
      "seed": 4002,
      "template": "registry_persistence",
      "mode": "provocateur",
      "ok": true,
      "wall_s": 9.82,
      "chain_ok": true,
      "chain_reason": null,
      "tp": 0,
      "fp": 0,
      "fn": 1,
      "fp_planted": 0,
      "precision": 0.0,
      "recall": 0.0,
      "f1": 0.0,
      "n_findings": 0
    },
    {
      "seed": 4003,
      "template": "registry_persistence",
      "mode": "provocateur",
      "ok": true,
      "wall_s": 9.21,
      "chain_ok": true,
      "chain_reason": null,
      "tp": 0,
      "fp": 0,
      "fn": 1,
      "fp_planted": 0,
      "precision": 0.0,
      "recall": 0.0,
      "f1": 0.0,
      "n_findings": 0
    },
    {
      "seed": 4004,
      "template": "registry_persistence",
      "mode": "provocateur",
      "ok": true,
      "wall_s": 9.23,
      "chain_ok": true,
      "chain_reason": null,
      "tp": 0,
      "fp": 0,
      "fn": 1,
      "fp_planted": 0,
      "precision": 0.0,
      "recall": 0.0,
      "f1": 0.0,
      "n_findings": 0
    },
    {
      "seed": 4005,
      "template": "registry_persistence",
      "mode": "provocateur",
      "ok": true,
      "wall_s": 11.04,
      "chain_ok": true,
      "chain_reason": null,
      "tp": 0,
      "fp": 0,
      "fn": 1,
      "fp_planted": 0,
      "precision": 0.0,
      "recall": 0.0,
      "f1": 0.0,
      "n_findings": 0
    },
    {
      "seed": 4006,
      "template": "registry_persistence",
      "mode": "provocateur",
      "ok": true,
      "wall_s": 11.31,
      "chain_ok": true,
      "chain_reason": null,
      "tp": 0,
      "fp": 0,
      "fn": 1,
      "fp_planted": 0,
      "precision": 0.0,
      "recall": 0.0,
      "f1": 0.0,
      "n_findings": 0
    },
    {
      "seed": 4007,
      "template": "registry_persistence",
      "mode": "provocateur",
      "ok": true,
      "wall_s": 18.79,
      "chain_ok": true,
      "chain_reason": null,
      "tp": 1,
      "fp": 0,
      "fn": 0,
      "fp_planted": 0,
      "precision": 1.0,
      "recall": 1.0,
      "f1": 1.0,
      "n_findings": 1
    },
    {
      "seed": 4008,
      "template": "registry_persistence",
      "mode": "provocateur",
      "ok": true,
      "wall_s": 14.43,
      "chain_ok": true,
      "chain_reason": null,
      "tp": 1,
      "fp": 0,
      "fn": 0,
      "fp_planted": 0,
      "precision": 1.0,
      "recall": 1.0,
      "f1": 1.0,
      "n_findings": 1
    },
    {
      "seed": 4009,
      "template": "registry_persistence",
      "mode": "provocateur",
      "ok": true,
      "wall_s": 11.16,
      "chain_ok": true,
      "chain_reason": null,
      "tp": 0,
      "fp": 0,
      "fn": 1,
      "fp_planted": 0,
      "precision": 0.0,
      "recall": 0.0,
      "f1": 0.0,
      "n_findings": 0
    },
    {
      "seed": 4010,
      "template": "registry_persistence",
      "mode": "provocateur",
      "ok": true,
      "wall_s": 11.58,
      "chain_ok": true,
      "chain_reason": null,
      "tp": 1,
      "fp": 0,
      "fn": 0,
      "fp_planted": 0,
      "precision": 1.0,
      "recall": 1.0,
      "f1": 1.0,
      "n_findings": 1
    },
    {
      "seed": 4011,
      "template": "registry_persistence",
      "mode": "provocateur",
      "ok": true,
      "wall_s": 15.34,
      "chain_ok": true,
      "chain_reason": null,
      "tp": 1,
      "fp": 0,
      "fn": 0,
      "fp_planted": 0,
      "precision": 1.0,
      "recall": 1.0,
      "f1": 1.0,
      "n_findings": 1
    },
    {
      "seed": 4012,
      "template": "registry_persistence",
      "mode": "provocateur",
      "ok": true,
      "wall_s": 15.66,
      "chain_ok": true,
      "chain_reason": null,
      "tp": 0,
      "fp": 0,
      "fn": 1,
      "fp_planted": 0,
      "precision": 0.0,
      "recall": 0.0,
      "f1": 0.0,
      "n_findings": 0
    },
    {
      "seed": 4013,
      "template": "registry_persistence",
      "mode": "provocateur",
      "ok": true,
      "wall_s": 9.84,
      "chain_ok": true,
      "chain_reason": null,
      "tp": 1,
      "fp": 0,
      "fn": 0,
      "fp_planted": 0,
      "precision": 1.0,
      "recall": 1.0,
      "f1": 1.0,
      "n_findings": 1
    },
    {
      "seed": 4014,
      "template": "registry_persistence",
      "mode": "provocateur",
      "ok": true,
      "wall_s": 11.97,
      "chain_ok": true,
      "chain_reason": null,
      "tp": 0,
      "fp": 0,
      "fn": 1,
      "fp_planted": 0,
      "precision": 0.0,
      "recall": 0.0,
      "f1": 0.0,
      "n_findings": 0
    },
    {
      "seed": 4015,
      "template": "registry_persistence",
      "mode": "provocateur",
      "ok": true,
      "wall_s": 9.48,
      "chain_ok": true,
      "chain_reason": null,
      "tp": 0,
      "fp": 0,
      "fn": 1,
      "fp_planted": 0,
      "precision": 0.0,
      "recall": 0.0,
      "f1": 0.0,
      "n_findings": 0
    },
    {
      "seed": 4016,
      "template": "registry_persistence",
      "mode": "provocateur",
      "ok": true,
      "wall_s": 10.88,
      "chain_ok": true,
      "chain_reason": null,
      "tp": 0,
      "fp": 0,
      "fn": 1,
      "fp_planted": 0,
      "precision": 0.0,
      "recall": 0.0,
      "f1": 0.0,
      "n_findings": 0
    },
    {
      "seed": 4017,
      "template": "registry_persistence",
      "mode": "provocateur",
      "ok": true,
      "wall_s": 11.87,
      "chain_ok": true,
      "chain_reason": null,
      "tp": 1,
      "fp": 0,
      "fn": 0,
      "fp_planted": 0,
      "precision": 1.0,
      "recall": 1.0,
      "f1": 1.0,
      "n_findings": 1
    },
    {
      "seed": 4018,
      "template": "registry_persistence",
      "mode": "provocateur",
      "ok": true,
      "wall_s": 13.02,
      "chain_ok": true,
      "chain_reason": null,
      "tp": 0,
      "fp": 0,
      "fn": 1,
      "fp_planted": 0,
      "precision": 0.0,
      "recall": 0.0,
      "f1": 0.0,
      "n_findings": 0
    },
    {
      "seed": 4019,
      "template": "registry_persistence",
      "mode": "provocateur",
      "ok": true,
      "wall_s": 10.64,
      "chain_ok": true,
      "chain_reason": null,
      "tp": 0,
      "fp": 0,
      "fn": 1,
      "fp_planted": 0,
      "precision": 0.0,
      "recall": 0.0,
      "f1": 0.0,
      "n_findings": 0
    }
  ],
  "summary": {
    "normal": {
      "n_runs": 40,
      "f1_mean": 0.95,
      "f1_stdev": 0.2207,
      "f1_min": 0.0,
      "f1_max": 1.0,
      "precision_mean": 0.95,
      "recall_mean": 0.95,
      "total_fp_planted": 0,
      "wall_s_total": 436.9,
      "wall_s_per_run": 10.92
    },
    "provocateur": {
      "n_runs": 40,
      "f1_mean": 0.5,
      "f1_stdev": 0.5064,
      "f1_min": 0.0,
      "f1_max": 1.0,
      "precision_mean": 0.5,
      "recall_mean": 0.5,
      "total_fp_planted": 0,
      "wall_s_total": 477.3,
      "wall_s_per_run": 11.93
    }
  }
}