{
  "results": [
    {
      "seed": 7000,
      "template": "browser",
      "mode": "normal",
      "ok": true,
      "wall_s": 7.07,
      "chain_ok": true,
      "chain_reason": null,
      "hmac_ok": true,
      "hmac_reason": null,
      "tp": 1,
      "fp": 0,
      "fn": 0,
      "fp_planted": 0,
      "precision": 1.0,
      "recall": 1.0,
      "f1": 1.0,
      "n_findings": 1
    },
    {
      "seed": 7001,
      "template": "browser",
      "mode": "normal",
      "ok": true,
      "wall_s": 8.96,
      "chain_ok": true,
      "chain_reason": null,
      "hmac_ok": true,
      "hmac_reason": null,
      "tp": 1,
      "fp": 0,
      "fn": 0,
      "fp_planted": 0,
      "precision": 1.0,
      "recall": 1.0,
      "f1": 1.0,
      "n_findings": 1
    },
    {
      "seed": 7002,
      "template": "browser",
      "mode": "normal",
      "ok": true,
      "wall_s": 8.36,
      "chain_ok": true,
      "chain_reason": null,
      "hmac_ok": true,
      "hmac_reason": null,
      "tp": 1,
      "fp": 0,
      "fn": 0,
      "fp_planted": 0,
      "precision": 1.0,
      "recall": 1.0,
      "f1": 1.0,
      "n_findings": 1
    },
    {
      "seed": 7003,
      "template": "browser",
      "mode": "normal",
      "ok": true,
      "wall_s": 8.72,
      "chain_ok": true,
      "chain_reason": null,
      "hmac_ok": true,
      "hmac_reason": null,
      "tp": 0,
      "fp": 1,
      "fn": 1,
      "fp_planted": 0,
      "precision": 0.0,
      "recall": 0.0,
      "f1": 0.0,
      "n_findings": 1
    },
    {
      "seed": 7004,
      "template": "browser",
      "mode": "normal",
      "ok": true,
      "wall_s": 7.82,
      "chain_ok": true,
      "chain_reason": null,
      "hmac_ok": true,
      "hmac_reason": null,
      "tp": 1,
      "fp": 0,
      "fn": 0,
      "fp_planted": 0,
      "precision": 1.0,
      "recall": 1.0,
      "f1": 1.0,
      "n_findings": 1
    },
    {
      "seed": 7005,
      "template": "browser",
      "mode": "normal",
      "ok": true,
      "wall_s": 7.57,
      "chain_ok": true,
      "chain_reason": null,
      "hmac_ok": true,
      "hmac_reason": null,
      "tp": 1,
      "fp": 0,
      "fn": 0,
      "fp_planted": 0,
      "precision": 1.0,
      "recall": 1.0,
      "f1": 1.0,
      "n_findings": 1
    },
    {
      "seed": 7006,
      "template": "browser",
      "mode": "normal",
      "ok": true,
      "wall_s": 8.77,
      "chain_ok": true,
      "chain_reason": null,
      "hmac_ok": true,
      "hmac_reason": null,
      "tp": 1,
      "fp": 0,
      "fn": 0,
      "fp_planted": 0,
      "precision": 1.0,
      "recall": 1.0,
      "f1": 1.0,
      "n_findings": 1
    },
    {
      "seed": 7007,
      "template": "browser",
      "mode": "normal",
      "ok": true,
      "wall_s": 6.93,
      "chain_ok": true,
      "chain_reason": null,
      "hmac_ok": true,
      "hmac_reason": null,
      "tp": 1,
      "fp": 0,
      "fn": 0,
      "fp_planted": 0,
      "precision": 1.0,
      "recall": 1.0,
      "f1": 1.0,
      "n_findings": 1
    },
    {
      "seed": 7008,
      "template": "browser",
      "mode": "normal",
      "ok": true,
      "wall_s": 9.2,
      "chain_ok": true,
      "chain_reason": null,
      "hmac_ok": true,
      "hmac_reason": null,
      "tp": 1,
      "fp": 0,
      "fn": 0,
      "fp_planted": 0,
      "precision": 1.0,
      "recall": 1.0,
      "f1": 1.0,
      "n_findings": 1
    },
    {
      "seed": 7009,
      "template": "browser",
      "mode": "normal",
      "ok": true,
      "wall_s": 7.46,
      "chain_ok": true,
      "chain_reason": null,
      "hmac_ok": true,
      "hmac_reason": null,
      "tp": 1,
      "fp": 0,
      "fn": 0,
      "fp_planted": 0,
      "precision": 1.0,
      "recall": 1.0,
      "f1": 1.0,
      "n_findings": 1
    },
    {
      "seed": 7000,
      "template": "browser",
      "mode": "provocateur",
      "ok": true,
      "wall_s": 7.74,
      "chain_ok": true,
      "chain_reason": null,
      "hmac_ok": true,
      "hmac_reason": null,
      "tp": 0,
      "fp": 0,
      "fn": 1,
      "fp_planted": 0,
      "precision": 0.0,
      "recall": 0.0,
      "f1": 0.0,
      "n_findings": 0
    },
    {
      "seed": 7001,
      "template": "browser",
      "mode": "provocateur",
      "ok": true,
      "wall_s": 6.83,
      "chain_ok": true,
      "chain_reason": null,
      "hmac_ok": true,
      "hmac_reason": null,
      "tp": 0,
      "fp": 0,
      "fn": 1,
      "fp_planted": 0,
      "precision": 0.0,
      "recall": 0.0,
      "f1": 0.0,
      "n_findings": 0
    },
    {
      "seed": 7002,
      "template": "browser",
      "mode": "provocateur",
      "ok": true,
      "wall_s": 8.99,
      "chain_ok": true,
      "chain_reason": null,
      "hmac_ok": true,
      "hmac_reason": null,
      "tp": 0,
      "fp": 0,
      "fn": 1,
      "fp_planted": 0,
      "precision": 0.0,
      "recall": 0.0,
      "f1": 0.0,
      "n_findings": 0
    },
    {
      "seed": 7003,
      "template": "browser",
      "mode": "provocateur",
      "ok": true,
      "wall_s": 9.39,
      "chain_ok": true,
      "chain_reason": null,
      "hmac_ok": true,
      "hmac_reason": null,
      "tp": 0,
      "fp": 0,
      "fn": 1,
      "fp_planted": 0,
      "precision": 0.0,
      "recall": 0.0,
      "f1": 0.0,
      "n_findings": 0
    },
    {
      "seed": 7004,
      "template": "browser",
      "mode": "provocateur",
      "ok": true,
      "wall_s": 8.88,
      "chain_ok": true,
      "chain_reason": null,
      "hmac_ok": true,
      "hmac_reason": null,
      "tp": 0,
      "fp": 0,
      "fn": 1,
      "fp_planted": 0,
      "precision": 0.0,
      "recall": 0.0,
      "f1": 0.0,
      "n_findings": 0
    },
    {
      "seed": 7005,
      "template": "browser",
      "mode": "provocateur",
      "ok": true,
      "wall_s": 6.72,
      "chain_ok": true,
      "chain_reason": null,
      "hmac_ok": true,
      "hmac_reason": null,
      "tp": 0,
      "fp": 0,
      "fn": 1,
      "fp_planted": 0,
      "precision": 0.0,
      "recall": 0.0,
      "f1": 0.0,
      "n_findings": 0
    },
    {
      "seed": 7006,
      "template": "browser",
      "mode": "provocateur",
      "ok": true,
      "wall_s": 8.25,
      "chain_ok": true,
      "chain_reason": null,
      "hmac_ok": true,
      "hmac_reason": null,
      "tp": 1,
      "fp": 0,
      "fn": 0,
      "fp_planted": 0,
      "precision": 1.0,
      "recall": 1.0,
      "f1": 1.0,
      "n_findings": 1
    },
    {
      "seed": 7007,
      "template": "browser",
      "mode": "provocateur",
      "ok": true,
      "wall_s": 7.97,
      "chain_ok": true,
      "chain_reason": null,
      "hmac_ok": true,
      "hmac_reason": null,
      "tp": 0,
      "fp": 0,
      "fn": 1,
      "fp_planted": 0,
      "precision": 0.0,
      "recall": 0.0,
      "f1": 0.0,
      "n_findings": 0
    },
    {
      "seed": 7008,
      "template": "browser",
      "mode": "provocateur",
      "ok": true,
      "wall_s": 8.81,
      "chain_ok": true,
      "chain_reason": null,
      "hmac_ok": true,
      "hmac_reason": null,
      "tp": 0,
      "fp": 0,
      "fn": 1,
      "fp_planted": 0,
      "precision": 0.0,
      "recall": 0.0,
      "f1": 0.0,
      "n_findings": 0
    },
    {
      "seed": 7009,
      "template": "browser",
      "mode": "provocateur",
      "ok": true,
      "wall_s": 11.01,
      "chain_ok": true,
      "chain_reason": null,
      "hmac_ok": true,
      "hmac_reason": null,
      "tp": 1,
      "fp": 0,
      "fn": 0,
      "fp_planted": 0,
      "precision": 1.0,
      "recall": 1.0,
      "f1": 1.0,
      "n_findings": 1
    },
    {
      "seed": 7000,
      "template": "prefetch",
      "mode": "normal",
      "ok": true,
      "wall_s": 6.83,
      "chain_ok": true,
      "chain_reason": null,
      "hmac_ok": true,
      "hmac_reason": null,
      "tp": 0,
      "fp": 1,
      "fn": 1,
      "fp_planted": 0,
      "precision": 0.0,
      "recall": 0.0,
      "f1": 0.0,
      "n_findings": 1
    },
    {
      "seed": 7001,
      "template": "prefetch",
      "mode": "normal",
      "ok": true,
      "wall_s": 5.75,
      "chain_ok": true,
      "chain_reason": null,
      "hmac_ok": true,
      "hmac_reason": null,
      "tp": 0,
      "fp": 1,
      "fn": 1,
      "fp_planted": 0,
      "precision": 0.0,
      "recall": 0.0,
      "f1": 0.0,
      "n_findings": 1
    },
    {
      "seed": 7002,
      "template": "prefetch",
      "mode": "normal",
      "ok": true,
      "wall_s": 8.83,
      "chain_ok": true,
      "chain_reason": null,
      "hmac_ok": true,
      "hmac_reason": null,
      "tp": 0,
      "fp": 1,
      "fn": 1,
      "fp_planted": 0,
      "precision": 0.0,
      "recall": 0.0,
      "f1": 0.0,
      "n_findings": 1
    },
    {
      "seed": 7003,
      "template": "prefetch",
      "mode": "normal",
      "ok": true,
      "wall_s": 7.38,
      "chain_ok": true,
      "chain_reason": null,
      "hmac_ok": true,
      "hmac_reason": null,
      "tp": 0,
      "fp": 1,
      "fn": 1,
      "fp_planted": 0,
      "precision": 0.0,
      "recall": 0.0,
      "f1": 0.0,
      "n_findings": 1
    },
    {
      "seed": 7004,
      "template": "prefetch",
      "mode": "normal",
      "ok": true,
      "wall_s": 7.54,
      "chain_ok": true,
      "chain_reason": null,
      "hmac_ok": true,
      "hmac_reason": null,
      "tp": 0,
      "fp": 1,
      "fn": 1,
      "fp_planted": 0,
      "precision": 0.0,
      "recall": 0.0,
      "f1": 0.0,
      "n_findings": 1
    },
    {
      "seed": 7005,
      "template": "prefetch",
      "mode": "normal",
      "ok": true,
      "wall_s": 9.45,
      "chain_ok": true,
      "chain_reason": null,
      "hmac_ok": true,
      "hmac_reason": null,
      "tp": 0,
      "fp": 1,
      "fn": 1,
      "fp_planted": 0,
      "precision": 0.0,
      "recall": 0.0,
      "f1": 0.0,
      "n_findings": 1
    },
    {
      "seed": 7006,
      "template": "prefetch",
      "mode": "normal",
      "ok": true,
      "wall_s": 6.33,
      "chain_ok": true,
      "chain_reason": null,
      "hmac_ok": true,
      "hmac_reason": null,
      "tp": 0,
      "fp": 1,
      "fn": 1,
      "fp_planted": 0,
      "precision": 0.0,
      "recall": 0.0,
      "f1": 0.0,
      "n_findings": 1
    },
    {
      "seed": 7007,
      "template": "prefetch",
      "mode": "normal",
      "ok": true,
      "wall_s": 8.79,
      "chain_ok": true,
      "chain_reason": null,
      "hmac_ok": true,
      "hmac_reason": null,
      "tp": 0,
      "fp": 1,
      "fn": 1,
      "fp_planted": 0,
      "precision": 0.0,
      "recall": 0.0,
      "f1": 0.0,
      "n_findings": 1
    },
    {
      "seed": 7008,
      "template": "prefetch",
      "mode": "normal",
      "ok": true,
      "wall_s": 6.44,
      "chain_ok": true,
      "chain_reason": null,
      "hmac_ok": true,
      "hmac_reason": null,
      "tp": 0,
      "fp": 1,
      "fn": 1,
      "fp_planted": 0,
      "precision": 0.0,
      "recall": 0.0,
      "f1": 0.0,
      "n_findings": 1
    },
    {
      "seed": 7009,
      "template": "prefetch",
      "mode": "normal",
      "ok": true,
      "wall_s": 8.88,
      "chain_ok": true,
      "chain_reason": null,
      "hmac_ok": true,
      "hmac_reason": null,
      "tp": 0,
      "fp": 1,
      "fn": 1,
      "fp_planted": 0,
      "precision": 0.0,
      "recall": 0.0,
      "f1": 0.0,
      "n_findings": 1
    },
    {
      "seed": 7000,
      "template": "prefetch",
      "mode": "provocateur",
      "ok": true,
      "wall_s": 7.37,
      "chain_ok": true,
      "chain_reason": null,
      "hmac_ok": true,
      "hmac_reason": null,
      "tp": 0,
      "fp": 0,
      "fn": 1,
      "fp_planted": 0,
      "precision": 0.0,
      "recall": 0.0,
      "f1": 0.0,
      "n_findings": 0
    },
    {
      "seed": 7001,
      "template": "prefetch",
      "mode": "provocateur",
      "ok": true,
      "wall_s": 9.76,
      "chain_ok": true,
      "chain_reason": null,
      "hmac_ok": true,
      "hmac_reason": null,
      "tp": 0,
      "fp": 1,
      "fn": 1,
      "fp_planted": 0,
      "precision": 0.0,
      "recall": 0.0,
      "f1": 0.0,
      "n_findings": 1
    },
    {
      "seed": 7002,
      "template": "prefetch",
      "mode": "provocateur",
      "ok": true,
      "wall_s": 6.72,
      "chain_ok": true,
      "chain_reason": null,
      "hmac_ok": true,
      "hmac_reason": null,
      "tp": 0,
      "fp": 0,
      "fn": 1,
      "fp_planted": 0,
      "precision": 0.0,
      "recall": 0.0,
      "f1": 0.0,
      "n_findings": 0
    },
    {
      "seed": 7003,
      "template": "prefetch",
      "mode": "provocateur",
      "ok": true,
      "wall_s": 12.05,
      "chain_ok": true,
      "chain_reason": null,
      "hmac_ok": true,
      "hmac_reason": null,
      "tp": 0,
      "fp": 1,
      "fn": 1,
      "fp_planted": 0,
      "precision": 0.0,
      "recall": 0.0,
      "f1": 0.0,
      "n_findings": 1
    },
    {
      "seed": 7004,
      "template": "prefetch",
      "mode": "provocateur",
      "ok": true,
      "wall_s": 7.15,
      "chain_ok": true,
      "chain_reason": null,
      "hmac_ok": true,
      "hmac_reason": null,
      "tp": 0,
      "fp": 0,
      "fn": 1,
      "fp_planted": 0,
      "precision": 0.0,
      "recall": 0.0,
      "f1": 0.0,
      "n_findings": 0
    },
    {
      "seed": 7005,
      "template": "prefetch",
      "mode": "provocateur",
      "ok": true,
      "wall_s": 8.78,
      "chain_ok": true,
      "chain_reason": null,
      "hmac_ok": true,
      "hmac_reason": null,
      "tp": 0,
      "fp": 1,
      "fn": 1,
      "fp_planted": 0,
      "precision": 0.0,
      "recall": 0.0,
      "f1": 0.0,
      "n_findings": 1
    },
    {
      "seed": 7006,
      "template": "prefetch",
      "mode": "provocateur",
      "ok": true,
      "wall_s": 5.92,
      "chain_ok": true,
      "chain_reason": null,
      "hmac_ok": true,
      "hmac_reason": null,
      "tp": 0,
      "fp": 0,
      "fn": 1,
      "fp_planted": 0,
      "precision": 0.0,
      "recall": 0.0,
      "f1": 0.0,
      "n_findings": 0
    },
    {
      "seed": 7007,
      "template": "prefetch",
      "mode": "provocateur",
      "ok": true,
      "wall_s": 8.98,
      "chain_ok": true,
      "chain_reason": null,
      "hmac_ok": true,
      "hmac_reason": null,
      "tp": 0,
      "fp": 1,
      "fn": 1,
      "fp_planted": 0,
      "precision": 0.0,
      "recall": 0.0,
      "f1": 0.0,
      "n_findings": 1
    },
    {
      "seed": 7008,
      "template": "prefetch",
      "mode": "provocateur",
      "ok": true,
      "wall_s": 7.77,
      "chain_ok": true,
      "chain_reason": null,
      "hmac_ok": true,
      "hmac_reason": null,
      "tp": 0,
      "fp": 1,
      "fn": 1,
      "fp_planted": 0,
      "precision": 0.0,
      "recall": 0.0,
      "f1": 0.0,
      "n_findings": 1
    },
    {
      "seed": 7009,
      "template": "prefetch",
      "mode": "provocateur",
      "ok": true,
      "wall_s": 8.79,
      "chain_ok": true,
      "chain_reason": null,
      "hmac_ok": true,
      "hmac_reason": null,
      "tp": 0,
      "fp": 0,
      "fn": 1,
      "fp_planted": 0,
      "precision": 0.0,
      "recall": 0.0,
      "f1": 0.0,
      "n_findings": 0
    },
    {
      "seed": 7000,
      "template": "amcache",
      "mode": "normal",
      "ok": true,
      "wall_s": 7.95,
      "chain_ok": true,
      "chain_reason": null,
      "hmac_ok": true,
      "hmac_reason": null,
      "tp": 0,
      "fp": 1,
      "fn": 1,
      "fp_planted": 0,
      "precision": 0.0,
      "recall": 0.0,
      "f1": 0.0,
      "n_findings": 1
    },
    {
      "seed": 7001,
      "template": "amcache",
      "mode": "normal",
      "ok": true,
      "wall_s": 7.17,
      "chain_ok": true,
      "chain_reason": null,
      "hmac_ok": true,
      "hmac_reason": null,
      "tp": 0,
      "fp": 1,
      "fn": 1,
      "fp_planted": 0,
      "precision": 0.0,
      "recall": 0.0,
      "f1": 0.0,
      "n_findings": 1
    },
    {
      "seed": 7002,
      "template": "amcache",
      "mode": "normal",
      "ok": true,
      "wall_s": 6.5,
      "chain_ok": true,
      "chain_reason": null,
      "hmac_ok": true,
      "hmac_reason": null,
      "tp": 0,
      "fp": 1,
      "fn": 1,
      "fp_planted": 0,
      "precision": 0.0,
      "recall": 0.0,
      "f1": 0.0,
      "n_findings": 1
    },
    {
      "seed": 7003,
      "template": "amcache",
      "mode": "normal",
      "ok": true,
      "wall_s": 6.52,
      "chain_ok": true,
      "chain_reason": null,
      "hmac_ok": true,
      "hmac_reason": null,
      "tp": 0,
      "fp": 1,
      "fn": 1,
      "fp_planted": 0,
      "precision": 0.0,
      "recall": 0.0,
      "f1": 0.0,
      "n_findings": 1
    },
    {
      "seed": 7004,
      "template": "amcache",
      "mode": "normal",
      "ok": true,
      "wall_s": 8.37,
      "chain_ok": true,
      "chain_reason": null,
      "hmac_ok": true,
      "hmac_reason": null,
      "tp": 0,
      "fp": 1,
      "fn": 1,
      "fp_planted": 0,
      "precision": 0.0,
      "recall": 0.0,
      "f1": 0.0,
      "n_findings": 1
    },
    {
      "seed": 7005,
      "template": "amcache",
      "mode": "normal",
      "ok": true,
      "wall_s": 8.6,
      "chain_ok": true,
      "chain_reason": null,
      "hmac_ok": true,
      "hmac_reason": null,
      "tp": 0,
      "fp": 0,
      "fn": 1,
      "fp_planted": 0,
      "precision": 0.0,
      "recall": 0.0,
      "f1": 0.0,
      "n_findings": 0
    },
    {
      "seed": 7006,
      "template": "amcache",
      "mode": "normal",
      "ok": true,
      "wall_s": 7.23,
      "chain_ok": true,
      "chain_reason": null,
      "hmac_ok": true,
      "hmac_reason": null,
      "tp": 0,
      "fp": 1,
      "fn": 1,
      "fp_planted": 0,
      "precision": 0.0,
      "recall": 0.0,
      "f1": 0.0,
      "n_findings": 1
    },
    {
      "seed": 7007,
      "template": "amcache",
      "mode": "normal",
      "ok": true,
      "wall_s": 7.03,
      "chain_ok": true,
      "chain_reason": null,
      "hmac_ok": true,
      "hmac_reason": null,
      "tp": 0,
      "fp": 1,
      "fn": 1,
      "fp_planted": 0,
      "precision": 0.0,
      "recall": 0.0,
      "f1": 0.0,
      "n_findings": 1
    },
    {
      "seed": 7008,
      "template": "amcache",
      "mode": "normal",
      "ok": true,
      "wall_s": 7.66,
      "chain_ok": true,
      "chain_reason": null,
      "hmac_ok": true,
      "hmac_reason": null,
      "tp": 0,
      "fp": 1,
      "fn": 1,
      "fp_planted": 0,
      "precision": 0.0,
      "recall": 0.0,
      "f1": 0.0,
      "n_findings": 1
    },
    {
      "seed": 7009,
      "template": "amcache",
      "mode": "normal",
      "ok": true,
      "wall_s": 10.11,
      "chain_ok": true,
      "chain_reason": null,
      "hmac_ok": true,
      "hmac_reason": null,
      "tp": 0,
      "fp": 1,
      "fn": 1,
      "fp_planted": 0,
      "precision": 0.0,
      "recall": 0.0,
      "f1": 0.0,
      "n_findings": 1
    },
    {
      "seed": 7000,
      "template": "amcache",
      "mode": "provocateur",
      "ok": true,
      "wall_s": 6.66,
      "chain_ok": true,
      "chain_reason": null,
      "hmac_ok": true,
      "hmac_reason": null,
      "tp": 0,
      "fp": 0,
      "fn": 1,
      "fp_planted": 0,
      "precision": 0.0,
      "recall": 0.0,
      "f1": 0.0,
      "n_findings": 0
    },
    {
      "seed": 7001,
      "template": "amcache",
      "mode": "provocateur",
      "ok": true,
      "wall_s": 7.09,
      "chain_ok": true,
      "chain_reason": null,
      "hmac_ok": true,
      "hmac_reason": null,
      "tp": 0,
      "fp": 0,
      "fn": 1,
      "fp_planted": 0,
      "precision": 0.0,
      "recall": 0.0,
      "f1": 0.0,
      "n_findings": 0
    },
    {
      "seed": 7002,
      "template": "amcache",
      "mode": "provocateur",
      "ok": true,
      "wall_s": 6.67,
      "chain_ok": true,
      "chain_reason": null,
      "hmac_ok": true,
      "hmac_reason": null,
      "tp": 0,
      "fp": 0,
      "fn": 1,
      "fp_planted": 0,
      "precision": 0.0,
      "recall": 0.0,
      "f1": 0.0,
      "n_findings": 0
    },
    {
      "seed": 7003,
      "template": "amcache",
      "mode": "provocateur",
      "ok": true,
      "wall_s": 6.71,
      "chain_ok": true,
      "chain_reason": null,
      "hmac_ok": true,
      "hmac_reason": null,
      "tp": 0,
      "fp": 0,
      "fn": 1,
      "fp_planted": 0,
      "precision": 0.0,
      "recall": 0.0,
      "f1": 0.0,
      "n_findings": 0
    },
    {
      "seed": 7004,
      "template": "amcache",
      "mode": "provocateur",
      "ok": true,
      "wall_s": 11.36,
      "chain_ok": true,
      "chain_reason": null,
      "hmac_ok": true,
      "hmac_reason": null,
      "tp": 0,
      "fp": 1,
      "fn": 1,
      "fp_planted": 0,
      "precision": 0.0,
      "recall": 0.0,
      "f1": 0.0,
      "n_findings": 1
    },
    {
      "seed": 7005,
      "template": "amcache",
      "mode": "provocateur",
      "ok": true,
      "wall_s": 10.7,
      "chain_ok": true,
      "chain_reason": null,
      "hmac_ok": true,
      "hmac_reason": null,
      "tp": 0,
      "fp": 1,
      "fn": 1,
      "fp_planted": 0,
      "precision": 0.0,
      "recall": 0.0,
      "f1": 0.0,
      "n_findings": 1
    },
    {
      "seed": 7006,
      "template": "amcache",
      "mode": "provocateur",
      "ok": true,
      "wall_s": 5.92,
      "chain_ok": true,
      "chain_reason": null,
      "hmac_ok": true,
      "hmac_reason": null,
      "tp": 0,
      "fp": 0,
      "fn": 1,
      "fp_planted": 0,
      "precision": 0.0,
      "recall": 0.0,
      "f1": 0.0,
      "n_findings": 0
    },
    {
      "seed": 7007,
      "template": "amcache",
      "mode": "provocateur",
      "ok": true,
      "wall_s": 8.27,
      "chain_ok": true,
      "chain_reason": null,
      "hmac_ok": true,
      "hmac_reason": null,
      "tp": 0,
      "fp": 0,
      "fn": 1,
      "fp_planted": 0,
      "precision": 0.0,
      "recall": 0.0,
      "f1": 0.0,
      "n_findings": 0
    },
    {
      "seed": 7008,
      "template": "amcache",
      "mode": "provocateur",
      "ok": true,
      "wall_s": 8.29,
      "chain_ok": true,
      "chain_reason": null,
      "hmac_ok": true,
      "hmac_reason": null,
      "tp": 0,
      "fp": 1,
      "fn": 1,
      "fp_planted": 0,
      "precision": 0.0,
      "recall": 0.0,
      "f1": 0.0,
      "n_findings": 1
    },
    {
      "seed": 7009,
      "template": "amcache",
      "mode": "provocateur",
      "ok": true,
      "wall_s": 6.9,
      "chain_ok": true,
      "chain_reason": null,
      "hmac_ok": true,
      "hmac_reason": null,
      "tp": 0,
      "fp": 0,
      "fn": 1,
      "fp_planted": 0,
      "precision": 0.0,
      "recall": 0.0,
      "f1": 0.0,
      "n_findings": 0
    }
  ],
  "summary": {
    "normal": {
      "n_runs": 30,
      "f1_mean": 0.3,
      "f1_stdev": 0.4661,
      "f1_min": 0.0,
      "f1_max": 1.0,
      "precision_mean": 0.3,
      "recall_mean": 0.3,
      "total_fp_planted": 0,
      "wall_s_total": 234.2,
      "wall_s_per_run": 7.81
    },
    "provocateur": {
      "n_runs": 30,
      "f1_mean": 0.0667,
      "f1_stdev": 0.2537,
      "f1_min": 0.0,
      "f1_max": 1.0,
      "precision_mean": 0.0667,
      "recall_mean": 0.0667,
      "total_fp_planted": 0,
      "wall_s_total": 246.4,
      "wall_s_per_run": 8.21
    }
  }
}